helloworld.py
helloworld_travelip-0.0.2.dist-info/METADATA
helloworld_travelip-0.0.2.dist-info/WHEEL
helloworld_travelip-0.0.2.dist-info/top_level.txt
helloworld_travelip-0.0.2.dist-info/RECORD
