Metadata-Version: 2.1
Name: helloworld-travelip
Version: 0.0.2
Summary: Say Hello!
Home-page: UNKNOWN
Author: UNKNOWN
Author-email: UNKNOWN
License: UNKNOWN
Platform: UNKNOWN
